nsde/__init__.py
nsde/evolution_strategy.py
nsde/hv.cp37-win_amd64.pyd
nsde/nsde.py
nsde/openmdao.py
nsde/sorting.cp37-win_amd64.pyd
nsde/strategies/__init__.py
nsde/strategies/crossover.py
nsde/strategies/evolution.py
nsde/strategies/mutation.py
nsde/strategies/repair.py
nsde-0.1.1.dist-info/LICENSE.txt
nsde-0.1.1.dist-info/METADATA
nsde-0.1.1.dist-info/WHEEL
nsde-0.1.1.dist-info/top_level.txt
nsde-0.1.1.dist-info/RECORD
