Metadata-Version: 2.1
Name: nsde
Version: 0.1.1
Summary: Non-dominated Sorting Differential Evolution (NSDE) Algorithm
Home-page: https://github.com/daniel-de-vries/nsde
Author: Daniel de Vries
Author-email: danieldevries6@gmail.com
License: MIT License
Download-URL: https://github.com/daniel-de-vries/nsde/archive/v0.1.1.tar.gz
Keywords: optimization,black-box,data science,differential,evolution,evolutionary,algorithms,non-dominated,crowding distance,single-objective,multi-objective
Platform: UNKNOWN
Classifier: Development Status :: 4 - Beta
Classifier: Intended Audience :: Developers
Classifier: Intended Audience :: Science/Research
Classifier: License :: OSI Approved :: MIT License
Classifier: Natural Language :: English
Classifier: Operating System :: POSIX :: Linux
Classifier: Operating System :: MacOS :: MacOS X
Classifier: Operating System :: Microsoft :: Windows
Classifier: Programming Language :: C++
Classifier: Programming Language :: Python
Classifier: Programming Language :: Python :: 3
Classifier: Programming Language :: Python :: 3.6
Classifier: Programming Language :: Python :: 3.7
Classifier: Programming Language :: Python :: 3.8
Classifier: Topic :: Scientific/Engineering
Requires-Python: >=3.6, <4
Requires-Dist: numpy (>=1.17)
Requires-Dist: tqdm (<5,>=4.32)
Requires-Dist: pybind11 (>=2.4)
Provides-Extra: openmdao
Requires-Dist: openmdao (<4,>=2.10) ; extra == 'openmdao'
